[
  {
      "divid": "fraga1",
      "rubrik": "Fråga 1",
      "fraga": "Kan arbetsgivaren kräva att du gör ett drogtest när du söker jobb?",
      "alt1": "Ja",
      "value1": "rätt",
      "symbol1": "&#10004;",
      "alt2": "Nej",
      "value2": "fel",
      "symbol2": "&#x274C;",
      "alt3": "Donald Trump",
      "value3": "fel",
      "symbol3": "&#x274C;",
      "svar": "En privat arbetsgivare kan kräva att den som söker en tjänst ska göra ett drogtest. En arbetsgivare som är en kommun eller region kan kräva det om den kan visa att verksamheten motiverar detta, till exempel trafik och räddningstjänst."


  },
  {
      "divid": "fraga2",
      "rubrik": "Fråga 2",
      "fraga": "Kan arbetsgivaren kräva slumpmässiga drogtester av anställda i kommuner och regioner?",
      "alt1": "Ja",
      "value1": "fel",
      "symbol1": "&#x274C;",
      "alt2": "Nej",
      "value2": "rätt",
      "symbol2": "&#10004;",
      "alt3": "Syd",
      "value3": "fel",
      "symbol3": "&#x274C;",
      "svar": "För anställda i offentlig verksamhet sätter grundlagen stopp för drogtester."


  },
  {
      "divid": "fraga3",
      "rubrik": "Fråga 3",
      "fraga": "Måste du lämna drogtest om du är anställd i ett kommunalt eller regionalt bolag?",
      "alt1": "Ja",
      "value1": "rätt",
      "symbol1": "&#10004;",
      "alt2": "Nej",
      "value2": "fel",
      "symbol2": "&#x274C;",
      "alt3": "Syd",
      "value3": "fel",
      "symbol3": "&#x274C;",
      "svar": "Arbetsgivaren får kräva drogtest om vissa krav är uppfyllda, till exempel om du riskerar att skada andra om du är drogpåverkad på jobbet."
  },
  {
      "divid": "fraga4",
      "rubrik": "Fråga 4",
      "fraga": "Är du som privatanställd skyldig att lämna drogtest?",
      "alt1": "Ja",
      "value1": "rätt",
      "symbol1": "&#10004;",
      "alt2": "Nej",
      "value2": "fel",
      "symbol2": "&#x274C;",
      "alt3": "Syd",
      "value3": "fel",
      "symbol3": "&#x274C;",
      "svar": "Men den anställdes rätt till personlig integritet vägas mot arbetsgivarens intresse. Drogtest kan till exempel göras om någon ska köra tunga fordon eller arbeta med ungdomar som har missbruksproblem."
  },
  {
      "divid": "fraga5",
      "rubrik": "Fråga 5",
      "fraga": "Måste arbetsgivaren polisanmäla dig om testet är positivt?",
      "alt1": "Ja",
      "value1": "fel",
      "symbol1": "&#x274C;",
      "alt2": "Nej",
      "value2": "rätt",
      "symbol2": "&#10004;",
      "alt3": "Syd",
      "value3": "fel",
      "symbol3": "&#x274C;",
      "svar": "Arbetsgivaren är inte skyldig att polisanmäla."
  }
]
